{"job title": "Data Scientist", "company": "Parkview Health", "city state": "\u2013 Fort Wayne, IN", "rating": "3.7", "job description": "Summary:#Performs analysis of complex healthcare and varied data to develop innovations for pressing healthcare delivery challenges through visualization, machine learning, optimization and statistical inference solutions. Analyzes and models structured data and implements algorithms to support analysis using advanced statistical and mathematical methods from statistics, machine learning, data mining, and predictive modeling. Develops descriptive and predictive models, from conception to completion and provides long-term support. Performs exploratory data analysis, generates and tests working hypotheses, and uncovers interesting trends and relationships. Education:#Master#s Degree in Computer Science, Mathematics, Statistics or related quantitative discipline required. Ph.D. preferred. Experience:#Five or more years relevant quantitative and qualitative analytics experience using industry leading tools like Python, Azure, R, or SAS. Two or more years of healthcare related analytics experience required. Two or more years of experience working within EPIC data ecosystem a plus."}